Reqv/Rconn.py
Reqv/Rfetcher.py
Reqv/Rparser.py
Reqv/__init__.py
Reqv/utils.py
Reqv-0.0.5.dist-info/METADATA
Reqv-0.0.5.dist-info/WHEEL
Reqv-0.0.5.dist-info/top_level.txt
Reqv-0.0.5.dist-info/RECORD
