Metadata-Version: 2.1
Name: Reqv
Version: 0.0.5
Summary: A Python library for scraping data from APIs in modern websites.
Author: Vishva Allen
Author-email: jvishvateja26@gmail.com
License: MIT
Classifier: Programming Language :: Python :: 3
Classifier: License :: OSI Approved :: MIT License
Classifier: Operating System :: OS Independent
Requires-Dist: httpx
Requires-Dist: requests
